{
  "meta": {
    "year": 2017,
    "gp": "Sachsenring",
    "gp_name": "Sachsenring",
    "circuit": "Chronological Analysis Of Performances 19",
    "track_folder": "SACHSENRING",
    "session": "Q1",
    "session_long": "Grand Prix",
    "date": "2017-07-01",
    "class": "MotoGP",
    "source_file": "SACHSENRING/2017/GER_MGP_Q1.pdf",
    "parsed_at": "2026-06-23T21:41:53Z"
  },
  "riders": [
    {
      "position": 1,
      "number": "9",
      "name": "Danilo Petrucci",
      "nationality": "",
      "bike": "DUCATI",
      "team": "OCTO Pramac Racin",
      "summary": {
        "runs": 1,
        "total_laps": 10,
        "full_laps": null,
        "valid_laps": null,
        "best_lap": "1'27.688",
        "best_lap_sec": 87.688,
        "best_t1": 19.602,
        "best_t2": 25.109,
        "best_t3": 20.575,
        "best_t4": 22.402,
        "top_speed_kmh": 278.0
      },
      "laps": [
        {
          "run": 1,
          "lap": 1,
          "time": "1'58.814",
          "time_sec": 118.814,
          "t1": 44.348,
          "t2": 27.563,
          "t3": 22.933,
          "t4": 23.97,
          "top_speed_kmh": null,
          "type": "Flying"
        },
        {
          "run": 1,
          "lap": 2,
          "time": "1'30.961",
          "time_sec": 90.961,
          "t1": 20.446,
          "t2": 25.963,
          "t3": 21.411,
          "t4": 23.141,
          "top_speed_kmh": 267.0,
          "type": "Flying"
        },
        {
          "run": 1,
          "lap": 3,
          "time": "1'32.386",
          "time_sec": 92.386,
          "t1": 22.127,
          "t2": 26.112,
          "t3": 21.216,
          "t4": 22.931,
          "top_speed_kmh": 275.0,
          "type": "Flying"
        },
        {
          "run": 1,
          "lap": 4,
          "time": "1'28.878",
          "time_sec": 88.878,
          "t1": 19.861,
          "t2": 25.424,
          "t3": 20.904,
          "t4": 22.689,
          "top_speed_kmh": 280.0,
          "type": "Flying"
        },
        {
          "run": 1,
          "lap": 5,
          "time": "1'28.627",
          "time_sec": 88.627,
          "t1": 19.663,
          "t2": 25.501,
          "t3": 20.913,
          "t4": 22.55,
          "top_speed_kmh": 278.0,
          "type": "Flying"
        },
        {
          "run": 1,
          "lap": 6,
          "time": "1'28.144",
          "time_sec": 88.144,
          "t1": 19.674,
          "t2": 25.226,
          "t3": 20.633,
          "t4": 22.611,
          "top_speed_kmh": 276.0,
          "type": "Flying"
        },
        {
          "run": 1,
          "lap": 7,
          "time": "1'43.569",
          "time_sec": 103.569,
          "t1": 21.316,
          "t2": 33.036,
          "t3": 21.279,
          "t4": 27.938,
          "top_speed_kmh": 277.0,
          "type": "Flying"
        },
        {
          "run": 1,
          "lap": 8,
          "time": "1'27.688",
          "time_sec": 87.688,
          "t1": 19.602,
          "t2": 25.109,
          "t3": 20.575,
          "t4": 22.402,
          "top_speed_kmh": 278.0,
          "type": "Flying"
        },
        {
          "run": 1,
          "lap": 9,
          "time": "1'31.406",
          "time_sec": 91.406,
          "t1": 21.016,
          "t2": 26.067,
          "t3": 21.411,
          "t4": 22.912,
          "top_speed_kmh": 282.0,
          "type": "Flying"
        },
        {
          "run": 1,
          "lap": 10,
          "time": "1'31.678",
          "time_sec": 91.678,
          "t1": 19.55,
          "t2": 25.226,
          "t3": 20.77,
          "t4": 26.132,
          "top_speed_kmh": 281.0,
          "type": "Pit In"
        }
      ]
    },
    {
      "position": 2,
      "number": "44",
      "name": "Pol Espargaro",
      "nationality": "",
      "bike": "KTM",
      "team": "Red Bull KTM Factory S",
      "summary": {
        "runs": 1,
        "total_laps": 10,
        "full_laps": null,
        "valid_laps": null,
        "best_lap": "1'27.695",
        "best_lap_sec": 87.695,
        "best_t1": 19.511,
        "best_t2": 25.109,
        "best_t3": 20.62,
        "best_t4": 22.455,
        "top_speed_kmh": 274.0
      },
      "laps": [
        {
          "run": 1,
          "lap": 1,
          "time": "1'41.956",
          "time_sec": 101.956,
          "t1": 28.461,
          "t2": 27.297,
          "t3": 22.483,
          "t4": 23.715,
          "top_speed_kmh": null,
          "type": "Flying"
        },
        {
          "run": 1,
          "lap": 2,
          "time": "1'30.361",
          "time_sec": 90.361,
          "t1": 20.158,
          "t2": 25.974,
          "t3": 21.214,
          "t4": 23.015,
          "top_speed_kmh": 261.0,
          "type": "Flying"
        },
        {
          "run": 1,
          "lap": 3,
          "time": "1'42.885",
          "time_sec": 102.885,
          "t1": 20.091,
          "t2": 31.984,
          "t3": 22.007,
          "t4": 28.803,
          "top_speed_kmh": 268.0,
          "type": "Flying"
        },
        {
          "run": 1,
          "lap": 4,
          "time": "1'29.513",
          "time_sec": 89.513,
          "t1": 20.207,
          "t2": 25.575,
          "t3": 20.883,
          "t4": 22.848,
          "top_speed_kmh": 264.0,
          "type": "Flying"
        },
        {
          "run": 1,
          "lap": 5,
          "time": "1'33.314",
          "time_sec": 93.314,
          "t1": 20.095,
          "t2": 28.518,
          "t3": 21.376,
          "t4": 23.325,
          "top_speed_kmh": 259.0,
          "type": "Flying"
        },
        {
          "run": 1,
          "lap": 6,
          "time": "1'29.037",
          "time_sec": 89.037,
          "t1": 19.889,
          "t2": 25.469,
          "t3": 20.956,
          "t4": 22.723,
          "top_speed_kmh": 269.0,
          "type": "Flying"
        },
        {
          "run": 1,
          "lap": 7,
          "time": "1'28.542",
          "time_sec": 88.542,
          "t1": 19.847,
          "t2": 25.368,
          "t3": 20.655,
          "t4": 22.672,
          "top_speed_kmh": 275.0,
          "type": "Flying"
        },
        {
          "run": 1,
          "lap": 8,
          "time": "1'28.457",
          "time_sec": 88.457,
          "t1": 19.675,
          "t2": 25.268,
          "t3": 20.792,
          "t4": 22.722,
          "top_speed_kmh": 271.0,
          "type": "Flying"
        },
        {
          "run": 1,
          "lap": 9,
          "time": "1'28.016",
          "time_sec": 88.016,
          "t1": 19.648,
          "t2": 25.28,
          "t3": 20.655,
          "t4": 22.433,
          "top_speed_kmh": 277.0,
          "type": "Flying"
        },
        {
          "run": 1,
          "lap": 10,
          "time": "1'31.678",
          "time_sec": 91.678,
          "t1": 19.55,
          "t2": 25.226,
          "t3": 20.77,
          "t4": 26.132,
          "top_speed_kmh": 281.0,
          "type": "Pit In"
        },
        {
          "run": 1,
          "lap": 10,
          "time": "1'27.695",
          "time_sec": 87.695,
          "t1": 19.511,
          "t2": 25.109,
          "t3": 20.62,
          "t4": 22.455,
          "top_speed_kmh": 274.0,
          "type": "Flying"
        }
      ]
    },
    {
      "position": 3,
      "number": "43",
      "name": "Jack Miller",
      "nationality": "",
      "bike": "HONDA",
      "team": "EG 0,0 Marc VDS A",
      "summary": {
        "runs": 1,
        "total_laps": 8,
        "full_laps": null,
        "valid_laps": null,
        "best_lap": "1'27.695",
        "best_lap_sec": 87.695,
        "best_t1": 19.511,
        "best_t2": 25.109,
        "best_t3": 20.62,
        "best_t4": 22.455,
        "top_speed_kmh": 274.0
      },
      "laps": [
        {
          "run": 1,
          "lap": 1,
          "time": "1'41.464",
          "time_sec": 101.464,
          "t1": 27.032,
          "t2": 27.605,
          "t3": 22.996,
          "t4": 23.831,
          "top_speed_kmh": null,
          "type": "Flying"
        },
        {
          "run": 1,
          "lap": 2,
          "time": "1'30.430",
          "time_sec": 90.43,
          "t1": 20.299,
          "t2": 25.935,
          "t3": 21.295,
          "t4": 22.901,
          "top_speed_kmh": 269.0,
          "type": "Flying"
        },
        {
          "run": 1,
          "lap": 3,
          "time": "1'40.657",
          "time_sec": 100.657,
          "t1": 20.314,
          "t2": 31.415,
          "t3": 21.939,
          "t4": 26.989,
          "top_speed_kmh": 270.0,
          "type": "Flying"
        },
        {
          "run": 1,
          "lap": 4,
          "time": "1'28.991",
          "time_sec": 88.991,
          "t1": 19.883,
          "t2": 25.548,
          "t3": 20.96,
          "t4": 22.6,
          "top_speed_kmh": 275.0,
          "type": "Flying"
        },
        {
          "run": 1,
          "lap": 5,
          "time": "1'39.476",
          "time_sec": 99.476,
          "t1": 21.596,
          "t2": 33.071,
          "t3": 21.699,
          "t4": 23.11,
          "top_speed_kmh": 280.0,
          "type": "Flying"
        },
        {
          "run": 1,
          "lap": 6,
          "time": "1'27.967",
          "time_sec": 87.967,
          "t1": 19.678,
          "t2": 25.147,
          "t3": 20.723,
          "t4": 22.419,
          "top_speed_kmh": 275.0,
          "type": "Flying"
        },
        {
          "run": 1,
          "lap": 7,
          "time": "1'34.902",
          "time_sec": 94.902,
          "t1": 19.997,
          "t2": 26.842,
          "t3": 21.912,
          "t4": 26.151,
          "top_speed_kmh": 275.0,
          "type": "Flying"
        },
        {
          "run": 1,
          "lap": 8,
          "time": "1'35.292",
          "time_sec": 95.292,
          "t1": 19.799,
          "t2": 25.501,
          "t3": 21.527,
          "t4": 28.465,
          "top_speed_kmh": 271.0,
          "type": "Pit In"
        },
        {
          "run": 1,
          "lap": 10,
          "time": "1'27.695",
          "time_sec": 87.695,
          "t1": 19.511,
          "t2": 25.109,
          "t3": 20.62,
          "t4": 22.455,
          "top_speed_kmh": 274.0,
          "type": "Flying"
        }
      ]
    },
    {
      "position": 4,
      "number": "76",
      "name": "Loris Baz",
      "nationality": "",
      "bike": "DUCATI",
      "team": "Reale Avintia Racing F",
      "summary": {
        "runs": 1,
        "total_laps": 10,
        "full_laps": null,
        "valid_laps": null,
        "best_lap": "1'27.979",
        "best_lap_sec": 87.979,
        "best_t1": 19.516,
        "best_t2": 25.177,
        "best_t3": 20.615,
        "best_t4": 22.671,
        "top_speed_kmh": 276.4
      },
      "laps": [
        {
          "run": 1,
          "lap": 1,
          "time": "1'38.215",
          "time_sec": 98.215,
          "t1": 24.11,
          "t2": 27.618,
          "t3": 22.786,
          "t4": 23.701,
          "top_speed_kmh": null,
          "type": "Flying"
        },
        {
          "run": 1,
          "lap": 2,
          "time": "1'31.715",
          "time_sec": 91.715,
          "t1": 20.365,
          "t2": 26.127,
          "t3": 21.958,
          "t4": 23.265,
          "top_speed_kmh": 264.0,
          "type": "Flying"
        },
        {
          "run": 1,
          "lap": 3,
          "time": "1'30.342",
          "time_sec": 90.342,
          "t1": 20.044,
          "t2": 25.831,
          "t3": 21.385,
          "t4": 23.082,
          "top_speed_kmh": 270.0,
          "type": "Flying"
        },
        {
          "run": 1,
          "lap": 4,
          "time": "1'29.849",
          "time_sec": 89.849,
          "t1": 20.032,
          "t2": 25.66,
          "t3": 21.234,
          "t4": 22.923,
          "top_speed_kmh": 275.0,
          "type": "Flying"
        },
        {
          "run": 1,
          "lap": 5,
          "time": "1'29.287",
          "time_sec": 89.287,
          "t1": 19.766,
          "t2": 25.602,
          "t3": 21.167,
          "t4": 22.752,
          "top_speed_kmh": 278.0,
          "type": "Flying"
        },
        {
          "run": 1,
          "lap": 6,
          "time": "1'28.880",
          "time_sec": 88.88,
          "t1": 19.51,
          "t2": 25.45,
          "t3": 21.052,
          "t4": 22.868,
          "top_speed_kmh": 279.0,
          "type": "Flying"
        },
        {
          "run": 1,
          "lap": 7,
          "time": "1'28.826",
          "time_sec": 88.826,
          "t1": 19.802,
          "t2": 25.44,
          "t3": 20.823,
          "t4": 22.761,
          "top_speed_kmh": 273.0,
          "type": "Flying"
        },
        {
          "run": 1,
          "lap": 8,
          "time": "1'35.292",
          "time_sec": 95.292,
          "t1": 19.799,
          "t2": 25.501,
          "t3": 21.527,
          "t4": 28.465,
          "top_speed_kmh": 271.0,
          "type": "Pit In"
        },
        {
          "run": 1,
          "lap": 10,
          "time": "1'27.979",
          "time_sec": 87.979,
          "t1": 19.516,
          "t2": 25.177,
          "t3": 20.615,
          "t4": 22.671,
          "top_speed_kmh": 276.4,
          "type": "Flying"
        }
      ]
    },
    {
      "position": 5,
      "number": "38",
      "name": "Bradley Smith",
      "nationality": "",
      "bike": "KTM",
      "team": "Red Bull KTM FactoryGBR",
      "summary": {
        "runs": 1,
        "total_laps": 10,
        "full_laps": 9,
        "valid_laps": null,
        "best_lap": "1'27.979",
        "best_lap_sec": 87.979,
        "best_t1": 19.516,
        "best_t2": 25.177,
        "best_t3": 20.615,
        "best_t4": 22.671,
        "top_speed_kmh": 276.4
      },
      "laps": [
        {
          "run": 1,
          "lap": 1,
          "time": "1'49.170",
          "time_sec": 109.17,
          "t1": 35.348,
          "t2": 27.3,
          "t3": 22.655,
          "t4": 23.867,
          "top_speed_kmh": null,
          "type": "Flying"
        },
        {
          "run": 1,
          "lap": 2,
          "time": "1'32.751",
          "time_sec": 92.751,
          "t1": 20.7,
          "t2": 26.298,
          "t3": 22.121,
          "t4": 23.632,
          "top_speed_kmh": 256.7,
          "type": "Flying"
        },
        {
          "run": 1,
          "lap": 3,
          "time": "1'31.530",
          "time_sec": 91.53,
          "t1": 20.336,
          "t2": 26.05,
          "t3": 21.877,
          "t4": 23.267,
          "top_speed_kmh": 256.4,
          "type": "Flying"
        },
        {
          "run": 1,
          "lap": 4,
          "time": "1'30.657",
          "time_sec": 90.657,
          "t1": 20.2,
          "t2": 25.832,
          "t3": 21.574,
          "t4": 23.051,
          "top_speed_kmh": 260.4,
          "type": "Flying"
        },
        {
          "run": 1,
          "lap": 5,
          "time": "1'30.354",
          "time_sec": 90.354,
          "t1": 20.073,
          "t2": 25.609,
          "t3": 21.613,
          "t4": 23.059,
          "top_speed_kmh": 264.9,
          "type": "Flying"
        },
        {
          "run": 1,
          "lap": 6,
          "time": "1'29.546",
          "time_sec": 89.546,
          "t1": 20.006,
          "t2": 25.547,
          "t3": 21.063,
          "t4": 22.93,
          "top_speed_kmh": 261.6,
          "type": "Flying"
        },
        {
          "run": 1,
          "lap": 7,
          "time": "1'29.160",
          "time_sec": 89.16,
          "t1": 19.934,
          "t2": 25.34,
          "t3": 20.967,
          "t4": 22.919,
          "top_speed_kmh": 266.2,
          "type": "Flying"
        },
        {
          "run": 1,
          "lap": 10,
          "time": "1'27.979",
          "time_sec": 87.979,
          "t1": 19.516,
          "t2": 25.177,
          "t3": 20.615,
          "t4": 22.671,
          "top_speed_kmh": 276.4,
          "type": "Flying"
        },
        {
          "run": 1,
          "lap": 10,
          "time": "1'28.015",
          "time_sec": 88.015,
          "t1": 19.472,
          "t2": 25.115,
          "t3": 20.757,
          "t4": 22.671,
          "top_speed_kmh": 277.8,
          "type": "Flying"
        }
      ]
    },
    {
      "position": 6,
      "number": "29",
      "name": "Andrea Iannone",
      "nationality": "ITA",
      "bike": "SUZUKI",
      "team": "Team SUZUKI ECST",
      "summary": {
        "runs": 1,
        "total_laps": 10,
        "full_laps": 8,
        "valid_laps": null,
        "best_lap": "1'28.015",
        "best_lap_sec": 88.015,
        "best_t1": 19.472,
        "best_t2": 25.115,
        "best_t3": 20.757,
        "best_t4": 22.671,
        "top_speed_kmh": 277.8
      },
      "laps": [
        {
          "run": 1,
          "lap": 1,
          "time": "1'59.192",
          "time_sec": 119.192,
          "t1": 44.515,
          "t2": 27.485,
          "t3": 22.987,
          "t4": 24.205,
          "top_speed_kmh": null,
          "type": "Flying"
        },
        {
          "run": 1,
          "lap": 2,
          "time": "1'30.862",
          "time_sec": 90.862,
          "t1": 20.533,
          "t2": 25.702,
          "t3": 21.465,
          "t4": 23.162,
          "top_speed_kmh": 254.4,
          "type": "Flying"
        },
        {
          "run": 1,
          "lap": 3,
          "time": "1'33.637",
          "time_sec": 93.637,
          "t1": 22.391,
          "t2": 26.437,
          "t3": 21.656,
          "t4": 23.153,
          "top_speed_kmh": 259.3,
          "type": "Flying"
        },
        {
          "run": 1,
          "lap": 4,
          "time": "1'29.522",
          "time_sec": 89.522,
          "t1": 20.067,
          "t2": 25.461,
          "t3": 21.276,
          "t4": 22.718,
          "top_speed_kmh": 273.6,
          "type": "Flying"
        },
        {
          "run": 1,
          "lap": 5,
          "time": "1'28.506",
          "time_sec": 88.506,
          "t1": 19.738,
          "t2": 25.233,
          "t3": 21.01,
          "t4": 22.525,
          "top_speed_kmh": 278.2,
          "type": "Flying"
        },
        {
          "run": 1,
          "lap": 6,
          "time": "1'28.103",
          "time_sec": 88.103,
          "t1": 19.687,
          "t2": 24.988,
          "t3": 20.967,
          "t4": 22.461,
          "top_speed_kmh": 268.3,
          "type": "Flying"
        },
        {
          "run": 1,
          "lap": 7,
          "time": "1'34.921",
          "time_sec": 94.921,
          "t1": 19.666,
          "t2": 27.846,
          "t3": 21.687,
          "t4": 25.722,
          "top_speed_kmh": 270.0,
          "type": "Flying"
        },
        {
          "run": 1,
          "lap": 10,
          "time": "1'28.015",
          "time_sec": 88.015,
          "t1": 19.472,
          "t2": 25.115,
          "t3": 20.757,
          "t4": 22.671,
          "top_speed_kmh": 277.8,
          "type": "Flying"
        },
        {
          "run": 1,
          "lap": 10,
          "time": "1'47.767",
          "time_sec": 107.767,
          "t1": 29.366,
          "t2": 27.098,
          "t3": 23.137,
          "t4": 28.166,
          "top_speed_kmh": 280.6,
          "type": "Pit In"
        }
      ]
    },
    {
      "position": 7,
      "number": "36",
      "name": "Mika Kallio",
      "nationality": "FIN",
      "bike": "KTM",
      "team": "Red Bull KTM Factory",
      "summary": {
        "runs": 1,
        "total_laps": 10,
        "full_laps": 9,
        "valid_laps": null,
        "best_lap": "1'28.669",
        "best_lap_sec": 88.669,
        "best_t1": 20.06,
        "best_t2": 25.26,
        "best_t3": 20.723,
        "best_t4": 22.626,
        "top_speed_kmh": 267.0
      },
      "laps": [
        {
          "run": 1,
          "lap": 1,
          "time": "1'44.490",
          "time_sec": 104.49,
          "t1": 29.078,
          "t2": 27.917,
          "t3": 22.631,
          "t4": 24.864,
          "top_speed_kmh": null,
          "type": "Flying"
        },
        {
          "run": 1,
          "lap": 2,
          "time": "1'32.872",
          "time_sec": 92.872,
          "t1": 21.223,
          "t2": 26.45,
          "t3": 21.752,
          "t4": 23.447,
          "top_speed_kmh": 245.3,
          "type": "Flying"
        },
        {
          "run": 1,
          "lap": 3,
          "time": "1'36.937",
          "time_sec": 96.937,
          "t1": 20.711,
          "t2": 27.385,
          "t3": 21.62,
          "t4": 27.221,
          "top_speed_kmh": 248.4,
          "type": "Flying"
        },
        {
          "run": 1,
          "lap": 4,
          "time": "1'30.011",
          "time_sec": 90.011,
          "t1": 20.403,
          "t2": 25.743,
          "t3": 21.021,
          "t4": 22.844,
          "top_speed_kmh": 265.8,
          "type": "Flying"
        },
        {
          "run": 1,
          "lap": 5,
          "time": "1'29.817",
          "time_sec": 89.817,
          "t1": 20.15,
          "t2": 25.498,
          "t3": 21.232,
          "t4": 22.937,
          "top_speed_kmh": 259.8,
          "type": "Flying"
        },
        {
          "run": 1,
          "lap": 8,
          "time": "1'28.669",
          "time_sec": 88.669,
          "t1": 20.06,
          "t2": 25.26,
          "t3": 20.723,
          "t4": 22.626,
          "top_speed_kmh": 267.0,
          "type": "Flying"
        },
        {
          "run": 1,
          "lap": 10,
          "time": "1'47.767",
          "time_sec": 107.767,
          "t1": 29.366,
          "t2": 27.098,
          "t3": 23.137,
          "t4": 28.166,
          "top_speed_kmh": 280.6,
          "type": "Pit In"
        }
      ]
    },
    {
      "position": 8,
      "number": "8",
      "name": "Hector Barbera",
      "nationality": "SPA",
      "bike": "DUCATI",
      "team": "Reale Avintia Racing",
      "summary": {
        "runs": 1,
        "total_laps": 10,
        "full_laps": 9,
        "valid_laps": null,
        "best_lap": "1'28.404",
        "best_lap_sec": 88.404,
        "best_t1": 19.699,
        "best_t2": 25.28,
        "best_t3": 20.692,
        "best_t4": 22.733,
        "top_speed_kmh": 275.0
      },
      "laps": [
        {
          "run": 1,
          "lap": 1,
          "time": "1'48.373",
          "time_sec": 108.373,
          "t1": 33.01,
          "t2": 27.938,
          "t3": 23.165,
          "t4": 24.26,
          "top_speed_kmh": null,
          "type": "Flying"
        },
        {
          "run": 1,
          "lap": 2,
          "time": "1'32.529",
          "time_sec": 92.529,
          "t1": 20.991,
          "t2": 26.34,
          "t3": 21.755,
          "t4": 23.443,
          "top_speed_kmh": 255.0,
          "type": "Flying"
        },
        {
          "run": 1,
          "lap": 3,
          "time": "1'30.599",
          "time_sec": 90.599,
          "t1": 20.347,
          "t2": 25.773,
          "t3": 21.257,
          "t4": 23.222,
          "top_speed_kmh": 263.0,
          "type": "Flying"
        },
        {
          "run": 1,
          "lap": 4,
          "time": "1'29.691",
          "time_sec": 89.691,
          "t1": 20.097,
          "t2": 25.605,
          "t3": 21.117,
          "t4": 22.872,
          "top_speed_kmh": 267.0,
          "type": "Flying"
        },
        {
          "run": 1,
          "lap": 5,
          "time": "1'29.354",
          "time_sec": 89.354,
          "t1": 19.91,
          "t2": 25.734,
          "t3": 20.944,
          "t4": 22.766,
          "top_speed_kmh": 267.0,
          "type": "Flying"
        },
        {
          "run": 1,
          "lap": 6,
          "time": "1'28.528",
          "time_sec": 88.528,
          "t1": 19.73,
          "t2": 25.365,
          "t3": 20.826,
          "t4": 22.607,
          "top_speed_kmh": 275.0,
          "type": "Flying"
        },
        {
          "run": 1,
          "lap": 7,
          "time": "1'28.404",
          "time_sec": 88.404,
          "t1": 19.699,
          "t2": 25.28,
          "t3": 20.692,
          "t4": 22.733,
          "top_speed_kmh": 275.0,
          "type": "Flying"
        },
        {
          "run": 1,
          "lap": 8,
          "time": "1'31.004",
          "time_sec": 91.004,
          "t1": 19.612,
          "t2": 25.25,
          "t3": 20.904,
          "t4": 25.238,
          "top_speed_kmh": 273.0,
          "type": "Flying"
        },
        {
          "run": 1,
          "lap": 9,
          "time": "1'28.417",
          "time_sec": 88.417,
          "t1": 19.676,
          "t2": 25.246,
          "t3": 20.743,
          "t4": 22.752,
          "top_speed_kmh": 266.0,
          "type": "Flying"
        },
        {
          "run": 1,
          "lap": 10,
          "time": "1'30.730",
          "time_sec": 90.73,
          "t1": 21.466,
          "t2": 25.276,
          "t3": 20.84,
          "t4": 23.148,
          "top_speed_kmh": 269.0,
          "type": "Flying"
        }
      ]
    },
    {
      "position": 9,
      "number": "5",
      "name": "Johann Zarco",
      "nationality": "",
      "bike": "YAMAHA",
      "team": "Monster Yamaha Tec F",
      "summary": {
        "runs": 1,
        "total_laps": 9,
        "full_laps": null,
        "valid_laps": null,
        "best_lap": "1'28.444",
        "best_lap_sec": 88.444,
        "best_t1": 19.612,
        "best_t2": 25.357,
        "best_t3": 20.97,
        "best_t4": 22.505,
        "top_speed_kmh": 280.0
      },
      "laps": [
        {
          "run": 1,
          "lap": 2,
          "time": "1'34.506",
          "time_sec": 94.506,
          "t1": 21.322,
          "t2": 27.144,
          "t3": 22.403,
          "t4": 23.637,
          "top_speed_kmh": 252.0,
          "type": "Flying"
        },
        {
          "run": 1,
          "lap": 3,
          "time": "1'31.543",
          "time_sec": 91.543,
          "t1": 20.352,
          "t2": 26.161,
          "t3": 21.736,
          "t4": 23.294,
          "top_speed_kmh": 265.0,
          "type": "Flying"
        },
        {
          "run": 1,
          "lap": 4,
          "time": "1'30.243",
          "time_sec": 90.243,
          "t1": 20.167,
          "t2": 25.838,
          "t3": 21.189,
          "t4": 23.049,
          "top_speed_kmh": 267.0,
          "type": "Flying"
        },
        {
          "run": 1,
          "lap": 5,
          "time": "1'29.304",
          "time_sec": 89.304,
          "t1": 19.975,
          "t2": 25.588,
          "t3": 21.011,
          "t4": 22.73,
          "top_speed_kmh": 274.0,
          "type": "Flying"
        },
        {
          "run": 1,
          "lap": 6,
          "time": "1'28.701",
          "time_sec": 88.701,
          "t1": 19.674,
          "t2": 25.439,
          "t3": 20.95,
          "t4": 22.638,
          "top_speed_kmh": 278.0,
          "type": "Flying"
        },
        {
          "run": 1,
          "lap": 7,
          "time": "1'28.506",
          "time_sec": 88.506,
          "t1": 19.689,
          "t2": 25.266,
          "t3": 20.913,
          "t4": 22.638,
          "top_speed_kmh": 276.0,
          "type": "Flying"
        },
        {
          "run": 1,
          "lap": 8,
          "time": "1'28.783",
          "time_sec": 88.783,
          "t1": 19.623,
          "t2": 25.355,
          "t3": 21.07,
          "t4": 22.735,
          "top_speed_kmh": 276.0,
          "type": "Flying"
        },
        {
          "run": 1,
          "lap": 9,
          "time": "1'28.444",
          "time_sec": 88.444,
          "t1": 19.612,
          "t2": 25.357,
          "t3": 20.97,
          "t4": 22.505,
          "top_speed_kmh": 280.0,
          "type": "Flying"
        },
        {
          "run": 1,
          "lap": 10,
          "time": "1'30.730",
          "time_sec": 90.73,
          "t1": 21.466,
          "t2": 25.276,
          "t3": 20.84,
          "t4": 23.148,
          "top_speed_kmh": 269.0,
          "type": "Flying"
        }
      ]
    },
    {
      "position": 10,
      "number": "17",
      "name": "Karel Abraham",
      "nationality": "",
      "bike": "DUCATI",
      "team": "Pull&Bear Aspar Tea C",
      "summary": {
        "runs": 1,
        "total_laps": 10,
        "full_laps": null,
        "valid_laps": null,
        "best_lap": "1'28.444",
        "best_lap_sec": 88.444,
        "best_t1": 19.612,
        "best_t2": 25.357,
        "best_t3": 20.97,
        "best_t4": 22.505,
        "top_speed_kmh": 280.0
      },
      "laps": [
        {
          "run": 1,
          "lap": 1,
          "time": "1'42.289",
          "time_sec": 102.289,
          "t1": 25.625,
          "t2": 28.631,
          "t3": 23.544,
          "t4": 24.489,
          "top_speed_kmh": null,
          "type": "Flying"
        },
        {
          "run": 1,
          "lap": 2,
          "time": "1'32.244",
          "time_sec": 92.244,
          "t1": 20.826,
          "t2": 26.266,
          "t3": 21.826,
          "t4": 23.326,
          "top_speed_kmh": 254.0,
          "type": "Flying"
        },
        {
          "run": 1,
          "lap": 3,
          "time": "1'31.501",
          "time_sec": 91.501,
          "t1": 20.248,
          "t2": 26.291,
          "t3": 21.698,
          "t4": 23.264,
          "top_speed_kmh": 266.0,
          "type": "Flying"
        },
        {
          "run": 1,
          "lap": 4,
          "time": "1'30.418",
          "time_sec": 90.418,
          "t1": 20.113,
          "t2": 25.806,
          "t3": 21.319,
          "t4": 23.18,
          "top_speed_kmh": 267.0,
          "type": "Flying"
        },
        {
          "run": 1,
          "lap": 5,
          "time": "1'29.915",
          "time_sec": 89.915,
          "t1": 20.137,
          "t2": 25.761,
          "t3": 21.175,
          "t4": 22.842,
          "top_speed_kmh": 272.0,
          "type": "Flying"
        },
        {
          "run": 1,
          "lap": 6,
          "time": "1'29.648",
          "time_sec": 89.648,
          "t1": 19.986,
          "t2": 25.62,
          "t3": 21.026,
          "t4": 23.016,
          "top_speed_kmh": 268.0,
          "type": "Flying"
        },
        {
          "run": 1,
          "lap": 7,
          "time": "1'29.469",
          "time_sec": 89.469,
          "t1": 19.956,
          "t2": 25.471,
          "t3": 20.9,
          "t4": 23.142,
          "top_speed_kmh": 270.0,
          "type": "Flying"
        },
        {
          "run": 1,
          "lap": 8,
          "time": "1'28.730",
          "time_sec": 88.73,
          "t1": 19.768,
          "t2": 25.272,
          "t3": 20.73,
          "t4": 22.96,
          "top_speed_kmh": 272.0,
          "type": "Flying"
        },
        {
          "run": 1,
          "lap": 9,
          "time": "1'28.444",
          "time_sec": 88.444,
          "t1": 19.612,
          "t2": 25.357,
          "t3": 20.97,
          "t4": 22.505,
          "top_speed_kmh": 280.0,
          "type": "Flying"
        },
        {
          "run": 1,
          "lap": 9,
          "time": "1'28.800",
          "time_sec": 88.8,
          "t1": 19.766,
          "t2": 25.397,
          "t3": 20.912,
          "t4": 22.725,
          "top_speed_kmh": 279.0,
          "type": "Flying"
        },
        {
          "run": 1,
          "lap": 10,
          "time": "1'28.625",
          "time_sec": 88.625,
          "t1": 19.624,
          "t2": 25.221,
          "t3": 20.881,
          "t4": 22.899,
          "top_speed_kmh": 280.0,
          "type": "Flying"
        }
      ]
    },
    {
      "position": 11,
      "number": "22",
      "name": "Sam Lowes",
      "nationality": "",
      "bike": "APRILIA",
      "team": "Aprilia Racing Team G",
      "summary": {
        "runs": 1,
        "total_laps": 10,
        "full_laps": null,
        "valid_laps": null,
        "best_lap": "1'28.625",
        "best_lap_sec": 88.625,
        "best_t1": 19.624,
        "best_t2": 25.221,
        "best_t3": 20.881,
        "best_t4": 22.899,
        "top_speed_kmh": 280.0
      },
      "laps": [
        {
          "run": 1,
          "lap": 1,
          "time": "2'10.688",
          "time_sec": 130.688,
          "t1": 54.208,
          "t2": 28.604,
          "t3": 23.45,
          "t4": 24.426,
          "top_speed_kmh": null,
          "type": "Flying"
        },
        {
          "run": 1,
          "lap": 2,
          "time": "1'34.408",
          "time_sec": 94.408,
          "t1": 21.016,
          "t2": 27.421,
          "t3": 22.102,
          "t4": 23.869,
          "top_speed_kmh": 258.0,
          "type": "Flying"
        },
        {
          "run": 1,
          "lap": 3,
          "time": "1'31.873",
          "time_sec": 91.873,
          "t1": 20.484,
          "t2": 26.457,
          "t3": 21.526,
          "t4": 23.406,
          "top_speed_kmh": 258.0,
          "type": "Flying"
        },
        {
          "run": 1,
          "lap": 4,
          "time": "1'30.662",
          "time_sec": 90.662,
          "t1": 20.446,
          "t2": 26.066,
          "t3": 21.167,
          "t4": 22.983,
          "top_speed_kmh": 263.0,
          "type": "Flying"
        },
        {
          "run": 1,
          "lap": 5,
          "time": "1'29.694",
          "time_sec": 89.694,
          "t1": 20.256,
          "t2": 25.705,
          "t3": 20.928,
          "t4": 22.805,
          "top_speed_kmh": 264.0,
          "type": "Flying"
        },
        {
          "run": 1,
          "lap": 6,
          "time": "1'29.587",
          "time_sec": 89.587,
          "t1": 20.07,
          "t2": 25.772,
          "t3": 20.93,
          "t4": 22.815,
          "top_speed_kmh": 268.0,
          "type": "Flying"
        },
        {
          "run": 1,
          "lap": 7,
          "time": "1'28.876",
          "time_sec": 88.876,
          "t1": 19.948,
          "t2": 25.634,
          "t3": 20.66,
          "t4": 22.634,
          "top_speed_kmh": 273.0,
          "type": "Flying"
        },
        {
          "run": 1,
          "lap": 8,
          "time": "1'28.713",
          "time_sec": 88.713,
          "t1": 19.7,
          "t2": 25.495,
          "t3": 20.81,
          "t4": 22.708,
          "top_speed_kmh": 276.0,
          "type": "Flying"
        },
        {
          "run": 1,
          "lap": 9,
          "time": "1'28.659",
          "time_sec": 88.659,
          "t1": 19.655,
          "t2": 25.614,
          "t3": 20.801,
          "t4": 22.589,
          "top_speed_kmh": 278.0,
          "type": "Flying"
        },
        {
          "run": 1,
          "lap": 10,
          "time": "1'28.625",
          "time_sec": 88.625,
          "t1": 19.624,
          "t2": 25.221,
          "t3": 20.881,
          "t4": 22.899,
          "top_speed_kmh": 280.0,
          "type": "Flying"
        }
      ]
    },
    {
      "position": 12,
      "number": "42",
      "name": "Alex Rins",
      "nationality": "",
      "bike": "SUZUKI",
      "team": "Team SUZUKI ECST S",
      "summary": {
        "runs": 1,
        "total_laps": 10,
        "full_laps": null,
        "valid_laps": null,
        "best_lap": "1'29.504",
        "best_lap_sec": 89.504,
        "best_t1": 19.911,
        "best_t2": 25.746,
        "best_t3": 20.984,
        "best_t4": 22.863,
        "top_speed_kmh": 278.0
      },
      "laps": [
        {
          "run": 1,
          "lap": 1,
          "time": "1'39.406",
          "time_sec": 99.406,
          "t1": 25.836,
          "t2": 27.522,
          "t3": 22.268,
          "t4": 23.78,
          "top_speed_kmh": null,
          "type": "Flying"
        },
        {
          "run": 1,
          "lap": 2,
          "time": "1'31.802",
          "time_sec": 91.802,
          "t1": 20.297,
          "t2": 26.372,
          "t3": 21.628,
          "t4": 23.505,
          "top_speed_kmh": 271.0,
          "type": "Flying"
        },
        {
          "run": 1,
          "lap": 3,
          "time": "1'30.283",
          "time_sec": 90.283,
          "t1": 20.195,
          "t2": 25.939,
          "t3": 21.217,
          "t4": 22.932,
          "top_speed_kmh": 268.0,
          "type": "Flying"
        },
        {
          "run": 1,
          "lap": 4,
          "time": "1'30.134",
          "time_sec": 90.134,
          "t1": 20.119,
          "t2": 25.911,
          "t3": 21.311,
          "t4": 22.793,
          "top_speed_kmh": 273.0,
          "type": "Flying"
        },
        {
          "run": 1,
          "lap": 5,
          "time": "1'29.566",
          "time_sec": 89.566,
          "t1": 19.876,
          "t2": 25.88,
          "t3": 21.064,
          "t4": 22.746,
          "top_speed_kmh": 275.0,
          "type": "Flying"
        },
        {
          "run": 1,
          "lap": 6,
          "time": "1'30.245",
          "time_sec": 90.245,
          "t1": 19.996,
          "t2": 26.048,
          "t3": 21.242,
          "t4": 22.959,
          "top_speed_kmh": 273.0,
          "type": "Flying"
        },
        {
          "run": 1,
          "lap": 7,
          "time": "1'29.504",
          "time_sec": 89.504,
          "t1": 19.911,
          "t2": 25.746,
          "t3": 20.984,
          "t4": 22.863,
          "top_speed_kmh": 278.0,
          "type": "Flying"
        }
      ]
    },
    {
      "position": 13,
      "number": "45",
      "name": "Scott Redding",
      "nationality": "GBR",
      "bike": "DUCATI",
      "team": "OCTO Pramac Racin",
      "summary": {
        "runs": 1,
        "total_laps": 10,
        "full_laps": 8,
        "valid_laps": null,
        "best_lap": "1'36.272",
        "best_lap_sec": 96.272,
        "best_t1": 24.891,
        "best_t2": 26.668,
        "best_t3": 21.554,
        "best_t4": 23.159,
        "top_speed_kmh": 274.3
      },
      "laps": [
        {
          "run": 1,
          "lap": 3,
          "time": "1'38.634",
          "time_sec": 98.634,
          "t1": 20.519,
          "t2": 26.252,
          "t3": 22.097,
          "t4": 29.766,
          "top_speed_kmh": 264.1,
          "type": "Flying"
        },
        {
          "run": 1,
          "lap": 6,
          "time": "1'36.272",
          "time_sec": 96.272,
          "t1": 24.891,
          "t2": 26.668,
          "t3": 21.554,
          "t4": 23.159,
          "top_speed_kmh": 274.3,
          "type": "Flying"
        }
      ]
    },
    {
      "position": 14,
      "number": "53",
      "name": "Tito Rabat",
      "nationality": "SPA",
      "bike": "HONDA",
      "team": "EG 0,0 Marc VDS",
      "summary": {
        "runs": 1,
        "total_laps": 10,
        "full_laps": 9,
        "valid_laps": null,
        "best_lap": "1'32.655",
        "best_lap_sec": 92.655,
        "best_t1": 21.365,
        "best_t2": 26.8,
        "best_t3": 21.439,
        "best_t4": 23.051,
        "top_speed_kmh": 269.5
      },
      "laps": [
        {
          "run": 1,
          "lap": 2,
          "time": "1'33.341",
          "time_sec": 93.341,
          "t1": 20.904,
          "t2": 26.744,
          "t3": 22.01,
          "t4": 23.683,
          "top_speed_kmh": 251.1,
          "type": "Flying"
        },
        {
          "run": 1,
          "lap": 5,
          "time": "1'32.655",
          "time_sec": 92.655,
          "t1": 21.365,
          "t2": 26.8,
          "t3": 21.439,
          "t4": 23.051,
          "top_speed_kmh": 269.5,
          "type": "Flying"
        }
      ]
    }
  ]
}